metaod
