Metadata-Version: 2.1
Name: metaod
Version: 0.0.6
Summary: Automating Outlier Detection via Meta-Learning (selece/recommend OD model(s) for new datasets)
Home-page: https://github.com/yzhao062/metaod
Author: Yue Zhao
Author-email: zhaoy@cmu.edu
License: UNKNOWN
Download-URL: https://github.com/yzhao062/metaod/archive/master.zip
Keywords: outlier detection,anomaly detection,outlier ensembles,data mining,meta learning,AutoML
Platform: UNKNOWN
Classifier: Development Status :: 2 - Pre-Alpha
Classifier: Intended Audience :: Education
Classifier: Intended Audience :: Financial and Insurance Industry
Classifier: Intended Audience :: Science/Research
Classifier: Intended Audience :: Developers
Classifier: Intended Audience :: Information Technology
Classifier: License :: OSI Approved :: BSD License
Classifier: Programming Language :: Python :: 3.5
Classifier: Programming Language :: Python :: 3.6
Classifier: Programming Language :: Python :: 3.7
